Ships.E.HTML
ships/LLM/LLM.O.HTML
ships/ML/ML.O.HTML
ships/Search/Search.s.HTML
ships/__init__.py
ships/_clique/__init__.py
ships/_license/license.s.HTML
ships/_license/licenses/gpl-3.0-standalone.html
ships/_status/.coverage
ships/_status/DB/records.json
ships/_status/ports.py
ships/_status/status.proc.py
ships/business/business.s.HTML
ships/business/decorators/decorators.r.HTML
ships/business/decorators/examples/example_1.py
ships/business/decorators/examples/multiple.py
ships/cadence/UTC/UTC.r.HTML
ships/cadence/UTC/current.py
ships/cadence/UTC/leap/seconds.py
ships/cadence/UTC/leap/years.py
ships/cadence/UTC/month/strings.py
ships/cadence/UTC/status_current.py
ships/cadence/filter/__init__.py
ships/cadence/filter/_status/status_1.py
ships/cadence/filter/_status/status_2.py
ships/cadence/filter/_status/status_3.py
ships/cadence/orbits/orbits.r.html
ships/clique.py
ships/coms/coms.r.HTML
ships/coms/protocols/SSH/SSH.r.HTML
ships/coms/protocols/SSL/SSL.r.HTML
ships/coms/wall/wall.r.HTML
ships/cycle/__init__.py
ships/cycle/cycle.S.HTML
ships/cycle/loops/__init__.py
ships/cycle/loops/loops.s.HTML
ships/cycle/loops/status_2.py
ships/cycle/loops/status_3.py
ships/cycle/loops/status_4.py
ships/cycle/params/__init__.py
ships/cycle/params/status_1.py
ships/cycle/params/status_2.py
ships/cycle/params_2/__init__.py
ships/cycle/params_2/status_1.py
ships/cycle/presents/__init__.py
ships/flow/demux_mux/__init__.py
ships/flow/demux_mux/_status/status_1.py
ships/flow/demux_mux/demux_mux.r.html
ships/flow/demux_mux2/__init__.py
ships/flow/demux_mux2/_status/status_1.py
ships/flow/flow.s.HTML
ships/flow/simultaneous/__init__.py
ships/flow/simultaneous_v2/__init__.py
ships/flow/simultaneous_v2/_status/status_1.py
ships/formats/ISO/ISO.s.HTML
ships/glamour/UTF8/one.HTML
ships/insure/equalities.py
ships/insure/equality.py
ships/insure/status_equalitites_1.py
ships/modules/exceptions/custom/__init__.py
ships/modules/exceptions/parse.py
ships/modules/fasten/__init__.py
ships/pexpect_4_9_0_copy/pexpect-4.9.0.dist-info/INSTALLER
ships/pexpect_4_9_0_copy/pexpect-4.9.0.dist-info/LICENSE
ships/pexpect_4_9_0_copy/pexpect-4.9.0.dist-info/METADATA
ships/pexpect_4_9_0_copy/pexpect-4.9.0.dist-info/RECORD
ships/pexpect_4_9_0_copy/pexpect-4.9.0.dist-info/REQUESTED
ships/pexpect_4_9_0_copy/pexpect-4.9.0.dist-info/WHEEL
ships/pexpect_4_9_0_copy/pexpect-4.9.0.dist-info/top_level.txt
ships-1.9.0.dist-info/METADATA
ships-1.9.0.dist-info/WHEEL
ships-1.9.0.dist-info/entry_points.txt
ships-1.9.0.dist-info/RECORD
