Metadata-Version: 2.1
Name: ships
Version: 1.9.0
Summary: Various counting tools
License: GPL-3.0-only
Requires-Python: >=3.10,<3.13
Classifier: License :: OSI Approved :: GNU General Public License v3 (GPLv3)
Classifier: Programming Language :: Python :: 3
Classifier: Programming Language :: Python :: 3.10
Classifier: Programming Language :: Python :: 3.11
Classifier: Programming Language :: Python :: 3.12
Requires-Dist: biotech (>=1.0.3,<2.0.0)
Requires-Dist: psutil (>=5.9.8,<6.0.0)
Requires-Dist: pydash (>=8.0.1,<9.0.0)
Requires-Dist: pyinotify (>=0.9.6,<0.10.0)
Requires-Dist: rich (>=13.7.1,<14.0.0)
